BlynkLib.py
ble_library.py
dht.py
i2c_lcd.py
lcd_api.py
servo.py
simpleBle.py
ssd1306.py
tcs34725.py
kocoafab-1.0.6.dist-info/METADATA
kocoafab-1.0.6.dist-info/WHEEL
kocoafab-1.0.6.dist-info/top_level.txt
kocoafab-1.0.6.dist-info/RECORD
