Metadata-Version: 2.1
Name: kocoafab
Version: 1.0.6
Summary: Library to get readings from sensors on a ESP32.
Home-page: https://kocoafab.cc
Author: kocoafab
Author-email: kocoafab@kocoa.or.kr
Classifier: Programming Language :: Python :: 3
Classifier: License :: OSI Approved :: MIT License
Classifier: Operating System :: OS Independent
Requires-Python: >=3.6
